MMonitor/__init__.py
MMonitor/extensions/__init__.py
MMonitor/extensions/extension.py
MMonitor/extensions/backward_extension/__init__.py
MMonitor/extensions/backward_extension/backward_input_extension.py
MMonitor/extensions/backward_extension/backward_output_eig_of_cov_extension.py
MMonitor/extensions/backward_extension/backward_output_extension.py
MMonitor/extensions/forward_extension/__init__.py
MMonitor/extensions/forward_extension/forward_input_eig_of_cov_extension.py
MMonitor/extensions/forward_extension/forward_input_extension.py
MMonitor/extensions/forward_extension/forward_output_extension.py
MMonitor/extensions/utils/__init__.py
MMonitor/extensions/utils/calculation.py
MMonitor/mmonitor/__init__.py
MMonitor/mmonitor/monitor.py
MMonitor/quantity/__init__.py
MMonitor/quantity/quantity.py
MMonitor/quantity/multistep/__init__.py
MMonitor/quantity/multistep/base_class.py
MMonitor/quantity/multistep/mean_tid.py
MMonitor/quantity/multistep/var_tid.py
MMonitor/quantity/multistep/weight_param_jump.py
MMonitor/quantity/singlestep/__init__.py
MMonitor/quantity/singlestep/attention_save.py
MMonitor/quantity/singlestep/backward_input_mean.py
MMonitor/quantity/singlestep/backward_input_norm.py
MMonitor/quantity/singlestep/backward_input_std.py
MMonitor/quantity/singlestep/backward_output_mean.py
MMonitor/quantity/singlestep/backward_output_norm.py
MMonitor/quantity/singlestep/backward_output_std.py
MMonitor/quantity/singlestep/base_class.py
MMonitor/quantity/singlestep/forward_input_cov_condition.py
MMonitor/quantity/singlestep/forward_input_cov_condition20.py
MMonitor/quantity/singlestep/forward_input_cov_condition50.py
MMonitor/quantity/singlestep/forward_input_cov_condition80.py
MMonitor/quantity/singlestep/forward_input_cov_max_eig.py
MMonitor/quantity/singlestep/forward_input_cov_stable_rank.py
MMonitor/quantity/singlestep/forward_input_mean.py
MMonitor/quantity/singlestep/forward_input_norm.py
MMonitor/quantity/singlestep/forward_input_std.py
MMonitor_pytorch-2.0.0.dist-info/LICENSE
MMonitor_pytorch-2.0.0.dist-info/METADATA
MMonitor_pytorch-2.0.0.dist-info/WHEEL
MMonitor_pytorch-2.0.0.dist-info/top_level.txt
MMonitor_pytorch-2.0.0.dist-info/RECORD
